main.py
ccpm_tools-0.1.7.dist-info/METADATA
ccpm_tools-0.1.7.dist-info/WHEEL
ccpm_tools-0.1.7.dist-info/entry_points.txt
ccpm_tools-0.1.7.dist-info/top_level.txt
ccpm_tools-0.1.7.dist-info/RECORD
