Metadata-Version: 2.4
Name: ccpm-tools
Version: 0.1.7
Summary: CLI Python tools for CCPM.
Project-URL: Homepage, https://github.com/Deleranax/ccpm
Project-URL: Issues, https://github.com/Deleranax/ccpm/issues
Requires-Python: >=3.12
Requires-Dist: typer-slim>=0.15
Requires-Dist: click<8.2
